{
  "8174": { "type": "mob", "name": "爆壳怪", "elemental": "none", "level": 1, "condition": "all", "isAshkin": false, "isElements": false, "mutation": "", "adaptation": "", "triggers": "", "triggerBy": "" },
  "8175": { "type": "mob", "name": "常风苔小妖", "elemental": "wind", "level": 1, "condition": "all", "isAshkin": false, "isElements": false, "mutation": "", "adaptation": "", "triggers": "", "triggerBy": "" },
  "8176": { "type": "mob", "name": "海陆鱼", "elemental": "none", "level": 1, "condition": "all", "isAshkin": false, "isElements": false, "mutation": "", "adaptation": "", "triggers": "", "triggerBy": "" },
  "8177": { "type": "mob", "name": "优雷卡尖叫雕", "elemental": "lightning", "level": 1, "condition": "all", "isAshkin": false, "isElements": false, "mutation": "", "adaptation": "", "triggers": "", "triggerBy": "" },
  "8178": { "type": "mob", "name": "海岸鮟鱇", "elemental": "none", "level": 1, "condition": "all", "isAshkin": false, "isElements": false, "mutation": "", "adaptation": "", "triggers": "", "triggerBy": "" },
  "8179": { "type": "mob", "name": "碎心大口花", "elemental": "none", "level": 1, "condition": "all", "isAshkin": false, "isElements": false, "mutation": "", "adaptation": "", "triggers": "", "triggerBy": "" },
  "8180": { "type": "mob", "name": "海岸食人鬼鮟鱇", "elemental": "none", "level": 1, "condition": "all", "isAshkin": false, "isElements": false, "mutation": "", "adaptation": "", "triggers": "", "triggerBy": "" },
  "8181": { "type": "mob", "name": "瓦尔魔花", "elemental": "none", "level": 1, "condition": "all", "isAshkin": false, "isElements": false, "mutation": "", "adaptation": "", "triggers": "", "triggerBy": "" },
  "8182": { "type": "mob", "name": "绿毛球", "elemental": "none", "level": 1, "condition": "all", "isAshkin": false, "isElements": false, "mutation": "", "adaptation": "", "triggers": "", "triggerBy": "" },
  "8183": { "type": "mob", "name": "离景水蛭", "elemental": "water", "level": 1, "condition": "all", "isAshkin": false, "isElements": false, "mutation": "", "adaptation": "", "triggers": "", "triggerBy": "" },
  "8184": { "type": "mob", "name": "仙人花", "elemental": "none", "level": 1, "condition": "all", "isAshkin": false, "isElements": false, "mutation": "", "adaptation": "", "triggers": "", "triggerBy": "" },
  "8185": { "type": "mob", "name": "林地犀蜴", "elemental": "none", "level": 1, "condition": "all", "isAshkin": false, "isElements": false, "mutation": "", "adaptation": "", "triggers": "", "triggerBy": "" },
  "8186": { "type": "mob", "name": "迁徙蚱蜢", "elemental": "none", "level": 1, "condition": "all", "isAshkin": false, "isElements": false, "mutation": "", "adaptation": "", "triggers": "", "triggerBy": "" },
  "8187": { "type": "mob", "name": "海祭司", "elemental": "none", "level": 1, "condition": "all", "isAshkin": false, "isElements": false, "mutation": "", "adaptation": "", "triggers": "", "triggerBy": "" },
  "8188": { "type": "mob", "name": "混种野猪", "elemental": "none", "level": 1, "condition": "all", "isAshkin": false, "isElements": false, "mutation": "", "adaptation": "", "triggers": "", "triggerBy": "" },
  "8189": { "type": "mob", "name": "常风哈佩亚鸟妖", "elemental": "wind", "level": 1, "condition": "all", "isAshkin": false, "isElements": false, "mutation": "", "adaptation": "", "triggers": "", "triggerBy": "" },
  "8190": { "type": "mob", "name": "晏蜓", "elemental": "none", "level": 1, "condition": "all", "isAshkin": false, "isElements": false, "mutation": "", "adaptation": "", "triggers": "", "triggerBy": "" },
  "8191": { "type": "mob", "name": "黑狼", "elemental": "none", "level": 1, "condition": "all", "isAshkin": false, "isElements": false, "mutation": "", "adaptation": "", "triggers": "", "triggerBy": "" },
  "8192": { "type": "mob", "name": "野性巴布拉斯", "elemental": "none", "level": 1, "condition": "all", "isAshkin": false, "isElements": false, "mutation": "", "adaptation": "", "triggers": "", "triggerBy": "" },
  "8193": { "type": "mob", "name": "瓦尔巨熊", "elemental": "none", "level": 1, "condition": "all", "isAshkin": false, "isElements": false, "mutation": "", "adaptation": "", "triggers": "", "triggerBy": "" },
  "8194": { "type": "mob", "name": "夺灵魔", "elemental": "none", "level": 1, "condition": "all", "isAshkin": false, "isElements": false, "mutation": "", "adaptation": "", "triggers": "", "triggerBy": "" },
  "8195": { "type": "mob", "name": "猎豹", "elemental": "none", "level": 1, "condition": "all", "isAshkin": false, "isElements": false, "mutation": "", "adaptation": "", "triggers": "", "triggerBy": "" },
  "8196": { "type": "mob", "name": "大脚怪", "elemental": "none", "level": 1, "condition": "all", "isAshkin": false, "isElements": false, "mutation": "", "adaptation": "", "triggers": "", "triggerBy": "" },
  "8197": { "type": "mob", "name": "瓦尔莱西", "elemental": "none", "level": 1, "condition": "all", "isAshkin": false, "isElements": false, "mutation": "", "adaptation": "", "triggers": "", "triggerBy": "" },
  "8198": { "type": "mob", "name": "阿卜拉克萨斯", "elemental": "none", "level": 1, "condition": "all", "isAshkin": false, "isElements": false, "mutation": "", "adaptation": "", "triggers": "", "triggerBy": "" },
  "8199": { "type": "mob", "name": "怖鳄", "elemental": "none", "level": 1, "condition": "all", "isAshkin": false, "isElements": false, "mutation": "", "adaptation": "", "triggers": "", "triggerBy": "" },
  "8200": { "type": "mob", "name": "追踪席兹", "elemental": "none", "level": 1, "condition": "all", "isAshkin": false, "isElements": false, "mutation": "", "adaptation": "", "triggers": "", "triggerBy": "" },
  "8201": { "type": "mob", "name": "古老古菩猩猩", "elemental": "none", "level": 1, "condition": "all", "isAshkin": false, "isElements": false, "mutation": "", "adaptation": "", "triggers": "", "triggerBy": "" },
  "8202": { "type": "mob", "name": "巨水蛇", "elemental": "water", "level": 1, "condition": "all", "isAshkin": false, "isElements": false, "mutation": "", "adaptation": "", "triggers": "", "triggerBy": "" },
  "8203": { "type": "mob", "name": "庭园守卫", "elemental": "none", "level": 1, "condition": "all", "isAshkin": false, "isElements": false, "mutation": "", "adaptation": "", "triggers": "", "triggerBy": "" },
  "8204": { "type": "mob", "name": "河道巨钳虾", "elemental": "none", "level": 1, "condition": "all", "isAshkin": false, "isElements": false, "mutation": "", "adaptation": "", "triggers": "", "triggerBy": "" },
  "8205": { "type": "mob", "name": "冰川巨像", "elemental": "ice", "level": 1, "condition": "all", "isAshkin": false, "isElements": false, "mutation": "", "adaptation": "", "triggers": "", "triggerBy": "" },
  "8206": { "type": "mob", "name": "常风腾云蛇", "elemental": "wind", "level": 1, "condition": "all", "isAshkin": false, "isElements": false, "mutation": "", "adaptation": "", "triggers": "", "triggerBy": "" },
  "8207": { "type": "mob", "name": "天仙子", "elemental": "none", "level": 1, "condition": "all", "isAshkin": false, "isElements": false, "mutation": "", "adaptation": "", "triggers": "", "triggerBy": "" },
  "8208": { "type": "mob", "name": "瓦尔斯卡尼特", "elemental": "none", "level": 1, "condition": "all", "isAshkin": false, "isElements": false, "mutation": "", "adaptation": "", "triggers": "", "triggerBy": "" },
  "8209": { "type": "mob", "name": "瓦尔比洛克", "elemental": "none", "level": 1, "condition": "all", "isAshkin": false, "isElements": false, "mutation": "", "adaptation": "", "triggers": "", "triggerBy": "" },
  "8210": { "type": "mob", "name": "独眼怪", "elemental": "none", "level": 1, "condition": "all", "isAshkin": false, "isElements": false, "mutation": "", "adaptation": "", "triggers": "", "triggerBy": "" },
  "8211": { "type": "mob", "name": "植生兽", "elemental": "none", "level": 1, "condition": "all", "isAshkin": false, "isElements": false, "mutation": "", "adaptation": "", "triggers": "", "triggerBy": "" },
  "8212": { "type": "mob", "name": "旧世界祖", "elemental": "none", "level": 1, "condition": "all", "isAshkin": false, "isElements": false, "mutation": "", "adaptation": "", "triggers": "", "triggerBy": "" },
  "8213": { "type": "mob", "name": "优雷卡扎哈克", "elemental": "lightning", "level": 1, "condition": "all", "isAshkin": false, "isElements": false, "mutation": "", "adaptation": "", "triggers": "", "triggerBy": "" },
  "8224": { "type": "nm", "name": "拉玛什图", "elemental": "none", "level": 1, "condition": "all", "isAshkin": false, "isElements": false, "mutation": "", "adaptation": "", "triggers": "", "triggerBy": "" },
  "8225": { "type": "nm", "name": "盖因", "elemental": "none", "level": 1, "condition": "all", "isAshkin": false, "isElements": false, "mutation": "", "adaptation": "", "triggers": "", "triggerBy": "" },
  "8226": { "type": "nm", "name": "庞巴德", "elemental": "none", "level": 1, "condition": "all", "isAshkin": false, "isElements": false, "mutation": "", "adaptation": "", "triggers": "", "triggerBy": "" },
  "8260": { "type": "elm", "name": "常风元灵", "elemental": "wind", "level": 1, "condition": "all", "isAshkin": false, "isElements": false, "mutation": "", "adaptation": "", "triggers": "", "triggerBy": "" },
  "8261": { "type": "mob", "name": "拉玛什图", "elemental": "none", "level": 1, "condition": "all", "isAshkin": false, "isElements": false, "mutation": "", "adaptation": "", "triggers": "", "triggerBy": "" },
  "8287": { "type": "nm", "name": "帕祖祖", "elemental": "none", "level": 20, "condition": "强风", "isAshkin": false, "isElements": false, "mutation": "", "adaptation": "", "triggers": "", "triggerBy": "8482" },
  "8394": { "type": "mob", "name": "恶灵之风", "elemental": "wind", "level": 1, "condition": "all", "isAshkin": false, "isElements": false, "mutation": "", "adaptation": "", "triggers": "", "triggerBy": "" },
  "8421": { "type": "mob", "name": "魔素风扇", "elemental": "wind", "level": 1, "condition": "all", "isAshkin": false, "isElements": false, "mutation": "", "adaptation": "", "triggers": "", "triggerBy": "" },
  "8422": { "type": "mob", "name": "四眼怪", "elemental": "none", "level": 1, "condition": "all", "isAshkin": false, "isElements": false, "mutation": "", "adaptation": "", "triggers": "", "triggerBy": "" },
  "8423": { "type": "mob", "name": "常风阿那罗", "elemental": "wind", "level": 1, "condition": "all", "isAshkin": false, "isElements": false, "mutation": "", "adaptation": "", "triggers": "", "triggerBy": "" },
  "8424": { "type": "mob", "name": "常风阿帕斯", "elemental": "wind", "level": 1, "condition": "all", "isAshkin": false, "isElements": false, "mutation": "", "adaptation": "", "triggers": "", "triggerBy": "" },
  "8425": { "type": "mob", "name": "古德斯德", "elemental": "none", "level": 1, "condition": "all", "isAshkin": false, "isElements": false, "mutation": "", "adaptation": "", "triggers": "", "triggerBy": "" },
  "8426": { "type": "mob", "name": "虚无鳞龙", "elemental": "none", "level": 1, "condition": "all", "isAshkin": false, "isElements": false, "mutation": "", "adaptation": "", "triggers": "", "triggerBy": "" },
  "8427": { "type": "mob", "name": "祖尼角龙", "elemental": "none", "level": 1, "condition": "all", "isAshkin": false, "isElements": false, "mutation": "", "adaptation": "", "triggers": "", "triggerBy": "" },
  "8428": { "type": "mob", "name": "曙象", "elemental": "none", "level": 1, "condition": "all", "isAshkin": false, "isElements": false, "mutation": "", "adaptation": "", "triggers": "", "triggerBy": "" },
  "8429": { "type": "mob", "name": "瓦尔妖影", "elemental": "none", "level": 1, "condition": "all", "isAshkin": false, "isElements": false, "mutation": "", "adaptation": "", "triggers": "", "triggerBy": "" },
  "8430": { "type": "mob", "name": "藻马", "elemental": "none", "level": 1, "condition": "all", "isAshkin": false, "isElements": false, "mutation": "", "adaptation": "", "triggers": "", "triggerBy": "" },
  "8471": { "type": "nm", "name": "雨元精", "elemental": "none", "level": 1, "condition": "all", "isAshkin": false, "isElements": true, "mutation": "", "adaptation": "", "triggers": "", "triggerBy": "" },
  "8472": { "type": "nm", "name": "雨元精", "elemental": "none", "level": 1, "condition": "all", "isAshkin": false, "isElements": true, "mutation": "", "adaptation": "", "triggers": "", "triggerBy": "" },
  "8473": { "type": "mob", "name": "雨元精", "elemental": "none", "level": 1, "condition": "all", "isAshkin": false, "isElements": true, "mutation": "", "adaptation": "", "triggers": "", "triggerBy": "" },
  "8474": { "type": "mob", "name": "台风元精", "elemental": "wind", "level": 1, "condition": "all", "isAshkin": false, "isElements": true, "mutation": "", "adaptation": "", "triggers": "", "triggerBy": "" },
  "8475": { "type": "mob", "name": "台风元精", "elemental": "wind", "level": 1, "condition": "all", "isAshkin": false, "isElements": true, "mutation": "", "adaptation": "", "triggers": "", "triggerBy": "" },
  "8476": { "type": "mob", "name": "台风元精", "elemental": "wind", "level": 1, "condition": "all", "isAshkin": false, "isElements": true, "mutation": "", "adaptation": "", "triggers": "", "triggerBy": "" },
  "8477": { "type": "mob", "name": "黄昏木乃伊", "elemental": "none", "level": 1, "condition": "all", "isAshkin": false, "isElements": false, "mutation": "", "adaptation": "", "triggers": "", "triggerBy": "" },
  "8478": { "type": "mob", "name": "贵族尸鬼", "elemental": "none", "level": 1, "condition": "all", "isAshkin": true, "isElements": false, "mutation": "", "adaptation": "", "triggers": "", "triggerBy": "" },
  "8479": { "type": "mob", "name": "黄昏浮灵", "elemental": "none", "level": 1, "condition": "all", "isAshkin": false, "isElements": false, "mutation": "", "adaptation": "", "triggers": "", "triggerBy": "" },
  "8480": { "type": "mob", "name": "古老贪吃鬼", "elemental": "none", "level": 1, "condition": "all", "isAshkin": false, "isElements": false, "mutation": "", "adaptation": "", "triggers": "", "triggerBy": "" },
  "8481": { "type": "mob", "name": "棺材守卫", "elemental": "none", "level": 1, "condition": "all", "isAshkin": false, "isElements": false, "mutation": "", "adaptation": "", "triggers": "", "triggerBy": "" },
  "8482": { "type": "mob", "name": "暗影幽灵", "elemental": "none", "level": 25, "condition": "夜晚", "isAshkin": false, "isElements": false, "mutation": "", "adaptation": "", "triggers": "8287", "triggerBy": "" },
  "8483": { "type": "nm", "name": "阔步西牟鸟", "elemental": "none", "level": 1, "condition": "all", "isAshkin": false, "isElements": false, "mutation": "", "adaptation": "", "triggers": "", "triggerBy": "" },
  "8484": { "type": "nm", "name": "塞尔凯特", "elemental": "none", "level": 1, "condition": "all", "isAshkin": false, "isElements": false, "mutation": "", "adaptation": "", "triggers": "", "triggerBy": "" },
  "8485": { "type": "nm", "name": "法夫纳", "elemental": "none", "level": 1, "condition": "all", "isAshkin": false, "isElements": false, "mutation": "", "adaptation": "", "triggers": "", "triggerBy": "" },
  "8486": { "type": "nm", "name": "常风皇帝", "elemental": "wind", "level": 1, "condition": "all", "isAshkin": false, "isElements": false, "mutation": "", "adaptation": "", "triggers": "", "triggerBy": "" },
  "8487": { "type": "nm", "name": "常风领主", "elemental": "wind", "level": 1, "condition": "all", "isAshkin": false, "isElements": false, "mutation": "", "adaptation": "", "triggers": "", "triggerBy": "" },
  "8488": { "type": "mob", "name": "龙化石", "elemental": "none", "level": 1, "condition": "all", "isAshkin": false, "isElements": false, "mutation": "", "adaptation": "", "triggers": "", "triggerBy": "" },
  "8547": { "type": "nm", "name": "科里多仙人刺", "elemental": "none", "level": 1, "condition": "all", "isAshkin": false, "isElements": false, "mutation": "", "adaptation": "", "triggers": "", "triggerBy": "" },
  "8549": { "type": "nm", "name": "阿米特", "elemental": "none", "level": 1, "condition": "all", "isAshkin": false, "isElements": false, "mutation": "", "adaptation": "", "triggers": "", "triggerBy": "" },
  "8550": { "type": "nm", "name": "波吕斐摩斯", "elemental": "none", "level": 1, "condition": "all", "isAshkin": false, "isElements": false, "mutation": "", "adaptation": "", "triggers": "", "triggerBy": "" },
  "8554": { "type": "nm", "name": "阿玛洛克", "elemental": "none", "level": 1, "condition": "all", "isAshkin": false, "isElements": false, "mutation": "", "adaptation": "", "triggers": "", "triggerBy": "" },
  "8555": { "type": "mob", "name": "虚无火花", "elemental": "fire", "level": 1, "condition": "all", "isAshkin": false, "isElements": false, "mutation": "", "adaptation": "", "triggers": "", "triggerBy": "" },
  "8559": { "type": "mob", "name": "帕祖祖的祭司", "elemental": "none", "level": 1, "condition": "all", "isAshkin": false, "isElements": false, "mutation": "", "adaptation": "", "triggers": "", "triggerBy": "" },
  "8560": { "type": "mob", "name": "帕祖祖的信徒", "elemental": "none", "level": 1, "condition": "all", "isAshkin": false, "isElements": false, "mutation": "", "adaptation": "", "triggers": "", "triggerBy": "" },
  "8567": { "type": "nm", "name": "极其危险物质", "elemental": "none", "level": 1, "condition": "all", "isAshkin": false, "isElements": false, "mutation": "", "adaptation": "", "triggers": "", "triggerBy": "" },
  "8568": { "type": "mob", "name": "危险物质", "elemental": "none", "level": 1, "condition": "all", "isAshkin": false, "isElements": false, "mutation": "", "adaptation": "", "triggers": "", "triggerBy": "" },
  "8569": { "type": "nm", "name": "哑弹", "elemental": "none", "level": 1, "condition": "all", "isAshkin": false, "isElements": false, "mutation": "", "adaptation": "", "triggers": "", "triggerBy": "" },
  "8572": { "type": "nm", "name": "毒孢子", "elemental": "none", "level": 1, "condition": "all", "isAshkin": false, "isElements": false, "mutation": "", "adaptation": "", "triggers": "", "triggerBy": "" },
  "8573": { "type": "nm", "name": "哲罕南", "elemental": "none", "level": 1, "condition": "all", "isAshkin": false, "isElements": false, "mutation": "", "adaptation": "", "triggers": "", "triggerBy": "" },
  "8574": { "type": "nm", "name": "群偶", "elemental": "none", "level": 1, "condition": "all", "isAshkin": false, "isElements": false, "mutation": "", "adaptation": "", "triggers": "", "triggerBy": "" },
  "8575": { "type": "mob", "name": "虚无裂痕", "elemental": "none", "level": 1, "condition": "all", "isAshkin": false, "isElements": false, "mutation": "", "adaptation": "", "triggers": "", "triggerBy": "" },
  "8576": { "type": "nm", "name": "卡利斯托", "elemental": "none", "level": 1, "condition": "all", "isAshkin": false, "isElements": false, "mutation": "", "adaptation": "", "triggers": "", "triggerBy": "" },
  "8597": { "type": "nm", "name": "白骑士", "elemental": "none", "level": 1, "condition": "all", "isAshkin": false, "isElements": false, "mutation": "", "adaptation": "", "triggers": "", "triggerBy": "" },
  "8604": { "type": "mob", "name": "死亡元精", "elemental": "none", "level": 1, "condition": "all", "isAshkin": true, "isElements": true, "mutation": "", "adaptation": "", "triggers": "", "triggerBy": "" },
  "8605": { "type": "mob", "name": "法夫纳", "elemental": "none", "level": 1, "condition": "all", "isAshkin": false, "isElements": false, "mutation": "", "adaptation": "", "triggers": "", "triggerBy": "" },
  "8636": { "type": "mob", "name": "贵族尸鬼", "elemental": "none", "level": 1, "condition": "all", "isAshkin": true, "isElements": false, "mutation": "", "adaptation": "", "triggers": "", "triggerBy": "" },
  "8637": { "type": "mob", "name": "毛旱獭", "elemental": "none", "level": 1, "condition": "all", "isAshkin": false, "isElements": false, "mutation": "", "adaptation": "", "triggers": "", "triggerBy": "" },
  "8638": { "type": "mob", "name": "水蟾蜍", "elemental": "water", "level": 1, "condition": "all", "isAshkin": false, "isElements": false, "mutation": "", "adaptation": "", "triggers": "", "triggerBy": "" },
  "8639": { "type": "mob", "name": "常风软糊怪", "elemental": "wind", "level": 1, "condition": "all", "isAshkin": false, "isElements": false, "mutation": "", "adaptation": "", "triggers": "", "triggerBy": "" },
  "8640": { "type": "mob", "name": "瓦尔亡魂", "elemental": "none", "level": 1, "condition": "all", "isAshkin": true, "isElements": false, "mutation": "", "adaptation": "", "triggers": "", "triggerBy": "" },
  "8641": { "type": "nm", "name": "暴雪元精", "elemental": "none", "level": 1, "condition": "all", "isAshkin": false, "isElements": true, "mutation": "", "adaptation": "", "triggers": "", "triggerBy": "" },
  "8642": { "type": "mob", "name": "黄昏蝙蝠", "elemental": "none", "level": 1, "condition": "all", "isAshkin": false, "isElements": false, "mutation": "", "adaptation": "", "triggers": "", "triggerBy": "" },
  "8643": { "type": "mob", "name": "瓦尔小魔精", "elemental": "none", "level": 1, "condition": "all", "isAshkin": false, "isElements": false, "mutation": "", "adaptation": "", "triggers": "", "triggerBy": "" },
  "8644": { "type": "mob", "name": "暴雪元精", "elemental": "none", "level": 1, "condition": "all", "isAshkin": false, "isElements": true, "mutation": "", "adaptation": "", "triggers": "", "triggerBy": "" },
  "8645": { "type": "mob", "name": "魔力爆弹怪", "elemental": "none", "level": 1, "condition": "all", "isAshkin": false, "isElements": false, "mutation": "", "adaptation": "", "triggers": "", "triggerBy": "" },
  "8646": { "type": "mob", "name": "黄昏浮灵", "elemental": "none", "level": 1, "condition": "all", "isAshkin": false, "isElements": false, "mutation": "", "adaptation": "", "triggers": "", "triggerBy": "" },
  "8647": { "type": "mob", "name": "不规则离子电", "elemental": "none", "level": 1, "condition": "all", "isAshkin": false, "isElements": false, "mutation": "", "adaptation": "", "triggers": "", "triggerBy": "" },
  "8648": { "type": "mob", "name": "愚火", "elemental": "fire", "level": 1, "condition": "all", "isAshkin": false, "isElements": false, "mutation": "", "adaptation": "", "triggers": "", "triggerBy": "" },
  "8649": { "type": "mob", "name": "野羚羊", "elemental": "none", "level": 1, "condition": "all", "isAshkin": false, "isElements": false, "mutation": "", "adaptation": "", "triggers": "", "triggerBy": "" },
  "8650": { "type": "mob", "name": "红菌帽", "elemental": "none", "level": 1, "condition": "all", "isAshkin": false, "isElements": false, "mutation": "", "adaptation": "", "triggers": "", "triggerBy": "" },
  "8653": { "type": "mob", "name": "晶狼", "elemental": "none", "level": 1, "condition": "all", "isAshkin": false, "isElements": false, "mutation": "", "adaptation": "", "triggers": "", "triggerBy": "" },
  "8654": { "type": "mob", "name": "魔力榴弹怪", "elemental": "none", "level": 1, "condition": "all", "isAshkin": false, "isElements": false, "mutation": "", "adaptation": "", "triggers": "", "triggerBy": "" },
  "8667": { "type": "mob", "name": "死衫蜂", "elemental": "none", "level": 1, "condition": "all", "isAshkin": false, "isElements": false, "mutation": "", "adaptation": "", "triggers": "", "triggerBy": "" },
  "8668": { "type": "mob", "name": "瓦尔雷蛟", "elemental": "lightning", "level": 1, "condition": "all", "isAshkin": false, "isElements": false, "mutation": "", "adaptation": "", "triggers": "", "triggerBy": "" },
  "8669": { "type": "mob", "name": "暴雪元精", "elemental": "none", "level": 1, "condition": "all", "isAshkin": false, "isElements": true, "mutation": "", "adaptation": "", "triggers": "", "triggerBy": "" },
  "8670": { "type": "mob", "name": "黄昏尸鬼", "elemental": "none", "level": 1, "condition": "all", "isAshkin": true, "isElements": false, "mutation": "", "adaptation": "", "triggers": "", "triggerBy": "" },
  "8671": { "type": "mob", "name": "常风跳蜥", "elemental": "wind", "level": 1, "condition": "all", "isAshkin": false, "isElements": false, "mutation": "", "adaptation": "", "triggers": "", "triggerBy": "" },
  "8672": { "type": "mob", "name": "黄昏尸鬼", "elemental": "none", "level": 1, "condition": "all", "isAshkin": true, "isElements": false, "mutation": "", "adaptation": "", "triggers": "", "triggerBy": "" },
  "8674": { "type": "mob", "name": "死亡面罩", "elemental": "none", "level": 1, "condition": "all", "isAshkin": true, "isElements": false, "mutation": "", "adaptation": "", "triggers": "", "triggerBy": "" },
  "8675": { "type": "mob", "name": "台风元精", "elemental": "wind", "level": 1, "condition": "all", "isAshkin": false, "isElements": true, "mutation": "", "adaptation": "", "triggers": "", "triggerBy": "" },
  "8676": { "type": "mob", "name": "精铁龟", "elemental": "none", "level": 1, "condition": "all", "isAshkin": false, "isElements": false, "mutation": "", "adaptation": "", "triggers": "", "triggerBy": "" },
  "8678": { "type": "nm", "name": "台风元精", "elemental": "wind", "level": 1, "condition": "all", "isAshkin": false, "isElements": true, "mutation": "", "adaptation": "", "triggers": "", "triggerBy": "" },
  "8681": { "type": "mob", "name": "死亡面罩", "elemental": "none", "level": 1, "condition": "all", "isAshkin": true, "isElements": false, "mutation": "", "adaptation": "", "triggers": "", "triggerBy": "" },
  "8682": { "type": "mob", "name": "钩蟹", "elemental": "none", "level": 1, "condition": "all", "isAshkin": false, "isElements": false, "mutation": "", "adaptation": "", "triggers": "", "triggerBy": "" },
  "8683": { "type": "nm", "name": "雨元精", "elemental": "none", "level": 1, "condition": "all", "isAshkin": false, "isElements": true, "mutation": "", "adaptation": "", "triggers": "", "triggerBy": "" },
  "8684": { "type": "nm", "name": "虚无加姆", "elemental": "none", "level": 1, "condition": "all", "isAshkin": false, "isElements": false, "mutation": "", "adaptation": "", "triggers": "", "triggerBy": "" },
  "8685": { "type": "nm", "name": "虚无裂痕", "elemental": "none", "level": 1, "condition": "all", "isAshkin": false, "isElements": false, "mutation": "", "adaptation": "", "triggers": "", "triggerBy": "" },
  "8687": { "type": "mob", "name": "台风元精", "elemental": "wind", "level": 1, "condition": "all", "isAshkin": false, "isElements": true, "mutation": "", "adaptation": "", "triggers": "", "triggerBy": "" },
  "8688": { "type": "mob", "name": "除霜爬虫", "elemental": "none", "level": 1, "condition": "all", "isAshkin": false, "isElements": false, "mutation": "", "adaptation": "", "triggers": "", "triggerBy": "" },
  "8689": { "type": "mob", "name": "武断花苞", "elemental": "none", "level": 1, "condition": "all", "isAshkin": false, "isElements": false, "mutation": "", "adaptation": "", "triggers": "", "triggerBy": "" },
  "8691": { "type": "nm", "name": "武断魔花茱莉卡", "elemental": "none", "level": 1, "condition": "all", "isAshkin": false, "isElements": false, "mutation": "", "adaptation": "", "triggers": "", "triggerBy": "" },
  "8692": { "type": "mob", "name": "虎头蜂", "elemental": "none", "level": 1, "condition": "all", "isAshkin": false, "isElements": false, "mutation": "", "adaptation": "", "triggers": "", "triggerBy": "" },
  "8693": { "type": "mob", "name": "雨元精", "elemental": "none", "level": 1, "condition": "all", "isAshkin": false, "isElements": true, "mutation": "", "adaptation": "", "triggers": "", "triggerBy": "" },
  "8694": { "type": "mob", "name": "黄昏无头骑士", "elemental": "none", "level": 1, "condition": "all", "isAshkin": false, "isElements": false, "mutation": "", "adaptation": "", "triggers": "", "triggerBy": "" },
  "8695": { "type": "mob", "name": "地狱风", "elemental": "wind", "level": 1, "condition": "all", "isAshkin": false, "isElements": false, "mutation": "", "adaptation": "", "triggers": "", "triggerBy": "" },
  "8696": { "type": "mob", "name": "猞猁", "elemental": "none", "level": 1, "condition": "all", "isAshkin": false, "isElements": false, "mutation": "", "adaptation": "", "triggers": "", "triggerBy": "" },
  "8697": { "type": "nm", "name": "雨元精", "elemental": "none", "level": 1, "condition": "all", "isAshkin": false, "isElements": true, "mutation": "", "adaptation": "", "triggers": "", "triggerBy": "" },
  "8698": { "type": "mob", "name": "黄昏无头骑士", "elemental": "none", "level": 1, "condition": "all", "isAshkin": false, "isElements": false, "mutation": "", "adaptation": "", "triggers": "", "triggerBy": "" },
  "8699": { "type": "mob", "name": "常风格雷姆林", "elemental": "wind", "level": 1, "condition": "all", "isAshkin": false, "isElements": false, "mutation": "", "adaptation": "", "triggers": "", "triggerBy": "" },
  "8700": { "type": "mob", "name": "黄昏无头骑士", "elemental": "none", "level": 1, "condition": "all", "isAshkin": false, "isElements": false, "mutation": "", "adaptation": "", "triggers": "", "triggerBy": "" },
  "8701": { "type": "mob", "name": "暗影之翼", "elemental": "none", "level": 1, "condition": "all", "isAshkin": false, "isElements": false, "mutation": "", "adaptation": "", "triggers": "", "triggerBy": "" },
  "8702": { "type": "mob", "name": "棺材守卫", "elemental": "none", "level": 1, "condition": "all", "isAshkin": false, "isElements": false, "mutation": "", "adaptation": "", "triggers": "", "triggerBy": "" },
  "8703": { "type": "mob", "name": "台风元精", "elemental": "wind", "level": 1, "condition": "all", "isAshkin": false, "isElements": true, "mutation": "", "adaptation": "", "triggers": "", "triggerBy": "" },
  "8704": { "type": "mob", "name": "棺材守卫", "elemental": "none", "level": 1, "condition": "all", "isAshkin": false, "isElements": false, "mutation": "", "adaptation": "", "triggers": "", "triggerBy": "" },
  "8705": { "type": "mob", "name": "噩梦长颈驼", "elemental": "none", "level": 1, "condition": "all", "isAshkin": false, "isElements": false, "mutation": "", "adaptation": "", "triggers": "", "triggerBy": "" },
  "8706": { "type": "mob", "name": "石鳍鲨", "elemental": "none", "level": 1, "condition": "all", "isAshkin": false, "isElements": false, "mutation": "", "adaptation": "", "triggers": "", "triggerBy": "" },
  "8707": { "type": "mob", "name": "常风天马", "elemental": "wind", "level": 1, "condition": "all", "isAshkin": false, "isElements": false, "mutation": "", "adaptation": "", "triggers": "", "triggerBy": "" },
  "8708": { "type": "nm", "name": "暴雪元精", "elemental": "none", "level": 1, "condition": "all", "isAshkin": false, "isElements": true, "mutation": "", "adaptation": "", "triggers": "", "triggerBy": "" },
  "8709": { "type": "mob", "name": "瓦尔蚁狮", "elemental": "none", "level": 1, "condition": "all", "isAshkin": false, "isElements": false, "mutation": "", "adaptation": "", "triggers": "", "triggerBy": "" },
  "8710": { "type": "mob", "name": "非凡裂钳蟹", "elemental": "none", "level": 1, "condition": "all", "isAshkin": false, "isElements": false, "mutation": "", "adaptation": "", "triggers": "", "triggerBy": "" },
  "8711": { "type": "mob", "name": "台风元精", "elemental": "wind", "level": 1, "condition": "all", "isAshkin": false, "isElements": true, "mutation": "", "adaptation": "", "triggers": "", "triggerBy": "" },
  "8712": { "type": "mob", "name": "常风阿里奥克", "elemental": "wind", "level": 1, "condition": "all", "isAshkin": false, "isElements": false, "mutation": "", "adaptation": "", "triggers": "", "triggerBy": "" },
  "8713": { "type": "mob", "name": "常风毕托所", "elemental": "wind", "level": 1, "condition": "all", "isAshkin": false, "isElements": false, "mutation": "", "adaptation": "", "triggers": "", "triggerBy": "" },
  "8715": { "type": "mob", "name": "台风元精", "elemental": "wind", "level": 1, "condition": "all", "isAshkin": false, "isElements": true, "mutation": "", "adaptation": "", "triggers": "", "triggerBy": "" }
}